.bumpversion.cfg
.virtualenv.dev-requirements.txt
.virtualenv.requirements.txt
LICENSE
MANIFEST.in
Makefile
README.rst
kiwi.yml
setup.cfg
setup.py
tox.ini
doc/Makefile
doc/build/man/kiwi.8
doc/build/man/kiwi::image::info.8
doc/build/man/kiwi::image::resize.8
doc/build/man/kiwi::result::bundle.8
doc/build/man/kiwi::result::list.8
doc/build/man/kiwi::system::build.8
doc/build/man/kiwi::system::create.8
doc/build/man/kiwi::system::prepare.8
doc/build/man/kiwi::system::update.8
doc/source/api.rst
doc/source/building_images.rst
doc/source/commands.rst
doc/source/concept_and_workflow.rst
doc/source/conf.py
doc/source/contributing.rst
doc/source/image_description.rst
doc/source/image_types_and_results.rst
doc/source/index.rst
doc/source/installation.rst
doc/source/overview.rst
doc/source/plugins.rst
doc/source/quickstart.rst
doc/source/troubleshooting.rst
doc/source/working_with_images.rst
doc/source/.images/intro.png
doc/source/.images/kiwi-logo.png
doc/source/.static/css/custom.css
doc/source/api/kiwi.archive.rst
doc/source/api/kiwi.boot.image.rst
doc/source/api/kiwi.boot.rst
doc/source/api/kiwi.bootloader.config.rst
doc/source/api/kiwi.bootloader.install.rst
doc/source/api/kiwi.bootloader.rst
doc/source/api/kiwi.bootloader.template.rst
doc/source/api/kiwi.builder.rst
doc/source/api/kiwi.container.rst
doc/source/api/kiwi.container.setup.rst
doc/source/api/kiwi.filesystem.rst
doc/source/api/kiwi.iso_tools.rst
doc/source/api/kiwi.package_manager.rst
doc/source/api/kiwi.partitioner.rst
doc/source/api/kiwi.repository.rst
doc/source/api/kiwi.repository.template.rst
doc/source/api/kiwi.rst
doc/source/api/kiwi.solver.repository.rst
doc/source/api/kiwi.solver.rst
doc/source/api/kiwi.storage.rst
doc/source/api/kiwi.storage.subformat.rst
doc/source/api/kiwi.storage.subformat.template.rst
doc/source/api/kiwi.system.rst
doc/source/api/kiwi.tasks.rst
doc/source/api/kiwi.utils.rst
doc/source/api/kiwi.volume_manager.rst
doc/source/building_images/build_container_image.rst
kiwi.egg-info/PKG-INFO
kiwi.egg-info/SOURCES.txt
kiwi.egg-info/dependency_links.txt
kiwi.egg-info/entry_points.txt
kiwi.egg-info/not-zip-safe
kiwi.egg-info/requires.txt
kiwi.egg-info/top_level.txt
