Metadata-Version: 2.1
Name: kiwi
Version: 9.25.14
Summary: KIWI - Appliance Builder (next generation)
Home-page: https://osinside.github.io/kiwi
Download-URL: https://download.opensuse.org/repositories/Virtualization:/Appliances:/Builder
Author: Marcus Schaefer
Author-email: ms@suse.com
License: GPLv3+
Classifier: Development Status :: 5 - Production/Stable
Classifier: Intended Audience :: Developers
Classifier: License :: OSI Approved :: GNU General Public License v3 or later (GPLv3+)
Classifier: Operating System :: POSIX :: Linux
Classifier: Programming Language :: Python :: 3.6
Classifier: Programming Language :: Python :: 3.7
Classifier: Topic :: System :: Operating System
Requires-Python: >=3.6
License-File: LICENSE
Requires-Dist: docopt>=0.6.2
Requires-Dist: lxml
Requires-Dist: requests
Requires-Dist: PyYAML
Requires-Dist: simplejson
Requires-Dist: typing_extensions; python_version < "3.8"
